puan_lite/__init__.py
puan_lite-0.1.4.dist-info/METADATA
puan_lite-0.1.4.dist-info/WHEEL
puan_lite-0.1.4.dist-info/RECORD
