Metadata-Version: 2.1
Name: puan-lite
Version: 0.1.4
Summary: 
Author: Rikard Olsson
Author-email: rikard@ourstudio.se
Requires-Python: >=3.9,<4.0
Classifier: Programming Language :: Python :: 3
Classifier: Programming Language :: Python :: 3.9
Classifier: Programming Language :: Python :: 3.10
Classifier: Programming Language :: Python :: 3.11
Requires-Dist: npycvx (>=0.0.2,<0.0.3)
Requires-Dist: puan (>=0.5.0,<0.6.0)
Requires-Dist: sympy (>=1.12,<2.0)
